logicparser/__init__.py
logicparser/main.py
logicparser/utils.py
logicparser-1.2.0.dist-info/LICENSE
logicparser-1.2.0.dist-info/METADATA
logicparser-1.2.0.dist-info/WHEEL
logicparser-1.2.0.dist-info/top_level.txt
logicparser-1.2.0.dist-info/RECORD
