Metadata-Version: 2.1
Name: logicparser
Version: 1.2.0
Summary: a free layer to create logics for your arguments
Home-page: https://github.com/mastrobirraio/logicparser
Author: Giuseppe "mastrobirraio" Matranga
Author-email: matrangagiuseppe99@gmail.com
Maintainer: Giuseppe "mastrobirraio" Matranga
License: MIT
Keywords: args,arguments,argparser,parser,logic,logicparser
Platform: UNKNOWN
Classifier: Operating System :: OS Independent
Classifier: Environment :: Console
Classifier: Intended Audience :: Developers
Classifier: Programming Language :: Python
Classifier: Programming Language :: Python :: 3
Classifier: Programming Language :: Python :: 3.6
Classifier: Programming Language :: Python :: 3.7
Classifier: Programming Language :: Python :: 3.8
Classifier: Programming Language :: Python :: Implementation :: CPython
Classifier: Programming Language :: Python :: Implementation :: PyPy
Classifier: Topic :: Terminals
Requires-Python: >=3.6
